oceandb_elasticsearch_driver/__init__.py
oceandb_elasticsearch_driver/indexes.py
oceandb_elasticsearch_driver/instance.py
oceandb_elasticsearch_driver/mapping.py
oceandb_elasticsearch_driver/plugin.py
oceandb_elasticsearch_driver/utils.py
oceandb_elasticsearch_driver-0.4.4.dist-info/LICENSE
oceandb_elasticsearch_driver-0.4.4.dist-info/METADATA
oceandb_elasticsearch_driver-0.4.4.dist-info/WHEEL
oceandb_elasticsearch_driver-0.4.4.dist-info/top_level.txt
oceandb_elasticsearch_driver-0.4.4.dist-info/RECORD
