Metadata-Version: 2.1
Name: oceandb-elasticsearch-driver
Version: 0.4.4
Summary: 🐳 OceanDB ElasticSearch Driver (Python).
Home-page: https://github.com/oceanprotocol/oceandb-elasticsearch-driver
Author: leucothia
Author-email: devops@oceanprotocol.com
License: Apache Software License 2.0
Keywords: oceandb-elasticsearch-driver
Platform: UNKNOWN
Classifier: Development Status :: 2 - Pre-Alpha
Classifier: Intended Audience :: Developers
Classifier: License :: OSI Approved :: Apache Software License
Classifier: Natural Language :: English
Classifier: Programming Language :: Python :: 3.4
Classifier: Programming Language :: Python :: 3.5
Classifier: Programming Language :: Python :: 3.6
Requires-Dist: oceandb-driver-interface
Requires-Dist: elasticsearch
